flowlauncher/FlowLauncher.py
flowlauncher/FlowLauncherAPI.py
flowlauncher/__init__.py
flowlauncher-0.1.1.dist-info/LICENSE
flowlauncher-0.1.1.dist-info/METADATA
flowlauncher-0.1.1.dist-info/WHEEL
flowlauncher-0.1.1.dist-info/top_level.txt
flowlauncher-0.1.1.dist-info/RECORD
