Metadata-Version: 2.1
Name: flowlauncher
Version: 0.1.1
Summary: Flow Launcher supports Python by JsonRPC.
Home-page: https://github.com/Flow-Launcher/Flow.Launcher.JsonRPC.Python
Author: Flow-Launcher
Author-email: Zeroto521@gmail.com
Maintainer: Zero
Maintainer-email: Zeroto521@gmail.com
License: MIT
Download-URL: https://github.com/Flow-Launcher/Flow.Launcher.JsonRPC.Python/archive/master.zip
Platform: Windows
Classifier: Development Status :: 3 - Alpha
Classifier: Intended Audience :: Developers
Classifier: License :: OSI Approved :: MIT License
Classifier: Natural Language :: English
Classifier: Operating System :: Microsoft :: Windows
Classifier: Programming Language :: Python
Classifier: Programming Language :: Python :: 3
Classifier: Programming Language :: Python :: 3 :: Only
Classifier: Programming Language :: Python :: 3.6
Classifier: Programming Language :: Python :: 3.7
Classifier: Programming Language :: Python :: 3.8
Classifier: Topic :: Software Development
Classifier: Topic :: Software Development :: Libraries
Classifier: Topic :: Software Development :: Libraries :: Application Frameworks
Requires: demjson
